constructor/20auto-upgrades
constructor/__init__.py
constructor/AWS.py
constructor/cli.py
constructor/Infrastructure.py
constructor/Instance.py
constructor/LocalMysql.py
constructor/SecurityGroup.py
constructor/SymfonyProject.py
constructor-0.1.0.dist-info/DESCRIPTION.rst
constructor-0.1.0.dist-info/entry_points.txt
constructor-0.1.0.dist-info/METADATA
constructor-0.1.0.dist-info/metadata.json
constructor-0.1.0.dist-info/RECORD
constructor-0.1.0.dist-info/top_level.txt
constructor-0.1.0.dist-info/WHEEL
