Metadata-Version: 2.0
Name: constructor
Version: 0.1.0
Summary: A tool for building up infrastructure.
Home-page: http://istvan-antal.github.io/constructor/
Author: István Miklós Antal
Author-email: istvan.m.antal@gmail.com
License: MIT
Keywords: infrastructure build provisioning aws automate
Platform: UNKNOWN
Classifier: Development Status :: 3 - Alpha
Classifier: Intended Audience :: Developers
Classifier: Topic :: Software Development :: Build Tools
Classifier: License :: OSI Approved :: MIT License
Classifier: Programming Language :: Python :: 2
Classifier: Programming Language :: Python :: 2.6
Classifier: Programming Language :: Python :: 2.7
Classifier: Programming Language :: Python :: 3
Classifier: Programming Language :: Python :: 3.2
Classifier: Programming Language :: Python :: 3.3
Classifier: Programming Language :: Python :: 3.4
Requires-Dist: awscli
